LICENSE
README.md
setup.py
lib/shotgrid/__init__.py
lib/shotgrid/asset.py
lib/shotgrid/base.py
lib/shotgrid/config.py
lib/shotgrid/delivery.py
lib/shotgrid/dotdictify.py
lib/shotgrid/logger.py
lib/shotgrid/media.py
lib/shotgrid/person.py
lib/shotgrid/playlist.py
lib/shotgrid/project.py
lib/shotgrid/sequence.py
lib/shotgrid/shot.py
lib/shotgrid/shotgrid.py
lib/shotgrid/step.py
lib/shotgrid/task.py
lib/shotgrid/version.py
lib/shotgrid.egg-info/PKG-INFO
lib/shotgrid.egg-info/SOURCES.txt
lib/shotgrid.egg-info/dependency_links.txt
lib/shotgrid.egg-info/not-zip-safe
lib/shotgrid.egg-info/requires.txt
lib/shotgrid.egg-info/top_level.txt
tests/test.py