Metadata-Version: 2.1
Name: shotgrid
Version: 0.3.0
Summary: Pythonic Shotgrid API wrapper
Home-page: http://github.com/rsgalloway/shotgrid
Author: Ryan Galloway
Author-email: ryan@rsgalloway.com
License: UNKNOWN
Platform: UNKNOWN
Requires-Python: >=3.8
